census/__init__.py
census/core.py
census/tests/__init__.py
census/tests/test_census.py
census_us-0.1.2.dist-info/LICENSE
census_us-0.1.2.dist-info/METADATA
census_us-0.1.2.dist-info/WHEEL
census_us-0.1.2.dist-info/top_level.txt
census_us-0.1.2.dist-info/RECORD
