Metadata-Version: 2.1
Name: census-us
Version: 0.1.2
Summary: Fork of a wrapper for the US Census Bureau's API
License: BSD
Platform: any
Classifier: Development Status :: 4 - Beta
Classifier: Intended Audience :: Developers
Classifier: License :: OSI Approved :: BSD License
Classifier: Natural Language :: English
Classifier: Operating System :: OS Independent
Classifier: Programming Language :: Python
License-File: LICENSE
Requires-Dist: requests (>=1.1.0)
